gentexdoc/__init__.py
gentexdoc/builtin.py
gentexdoc/generator.py
gentexdoc/main.py
gentexdoc/processing.py
gentexdoc/util.py
gentexdoc-0.4.1.dist-info/LICENSE
gentexdoc-0.4.1.dist-info/METADATA
gentexdoc-0.4.1.dist-info/WHEEL
gentexdoc-0.4.1.dist-info/entry_points.txt
gentexdoc-0.4.1.dist-info/top_level.txt
gentexdoc-0.4.1.dist-info/RECORD
