Metadata-Version: 2.1
Name: gentexdoc
Version: 0.4.1
Summary: Markdown to Latex to PDF generator
Home-page: https://gitlab.com/frPursuit/gentexdoc
Author: Pursuit
Author-email: fr.pursuit@gmail.com
License: GNU General Public License v3 (GPLv3)
Classifier: Programming Language :: Python :: 3
Classifier: License :: OSI Approved :: GNU General Public License v3 (GPLv3)
Classifier: Operating System :: OS Independent
Requires-Python: >=3.7
License-File: LICENSE
Requires-Dist: Jinja2 (>=3.1.2)
